week-3/Full-Adder-1/fulladder.v

module xor2(a, b, c);
input a, b;
output c;
assign c = a ^ b;
endmodule


module and2(a, b, c);
input a, b;
output c;
assign c = a & b;
endmodule


module or2(a, b, c);
input a, b;
output c;
assign c = a | b;
endmodule


module fa(i0, i1, cin, sum, cout);
input i0, i1, cin;
output sum, cout;
wire w1, w2, w3;
xor2 G1(i0, i1, w1);
xor2 G2(w1, cin, sum);
and2 G3(i0, i1, w2);
and2 G4(w1, cin, w3);
or2 G5(w2, w3, cout);

endmodule

week-3/Full-Adder-1/fulladder_tb.v
module tb_fulladder;

reg i0, i1, cin;
wire sum, cout;

fa FA1(i0, i1, cin, sum, cout);

initial
begin
    $dumpfile("fulladder.vcd");
    $dumpvars(0, tb_fulladder);

    $monitor($time,
             " i0=%b, i1=%b, cin=%b, sum=%b, cout=%b",
             i0, i1, cin, sum, cout);

    #0  i0=0; i1=0; cin=0;
    #20 i0=0; i1=0; cin=1;
    #20 i0=0; i1=1; cin=0;
    #20 i0=0; i1=1; cin=1;
    #20 i0=1; i1=0; cin=0;
    #20 i0=1; i1=0; cin=1;
    #20 i0=1; i1=1; cin=0;
    #20 i0=1; i1=1; cin=1;

    #20 $finish;
end

endmodule

week-3/Full-Adder-1/fulladder.vcd
$date
	Thu Aug 20 14:43:06 2026
$end
$version
	Icarus Verilog
$end
$timescale
	1s
$end
$scope module tb_fulladder $end
$var wire 1 ! cout $end
$var wire 1 " sum $end
$var reg 1 # cin $end
$var reg 1 $ i0 $end
$var reg 1 % i1 $end
$scope module FA1 $end
$var wire 1 & cin $end
$var wire 1 ! cout $end
$var wire 1 ' i0 $end
$var wire 1 ( i1 $end
$var wire 1 " sum $end
$var wire 1 ) w1 $end
$var wire 1 * w2 $end
$var wire 1 + w3 $end
$scope module G1 $end
$var wire 1 ' a $end
$var wire 1 ( b $end
$var wire 1 ) c $end
$upscope $end
$scope module G2 $end
$var wire 1 ) a $end
$var wire 1 & b $end
$var wire 1 " c $end
$upscope $end
$scope module G3 $end
$var wire 1 ' a $end
$var wire 1 ( b $end
$var wire 1 * c $end
$upscope $end
$scope module G4 $end
$var wire 1 ) a $end
$var wire 1 & b $end
$var wire 1 + c $end
$upscope $end
$scope module G5 $end
$var wire 1 * a $end
$var wire 1 + b $end
$var wire 1 ! c $end
$upscope $end
$upscope $end
$upscope $end
$enddefinitions $end
#0
$dumpvars
0+
0*
0)
0(
0'
0&
0%
0$
0#
0"
0!
$end
#20
1"
1#
1&
#40
1)
0#
0&
1%
1(
#60
1!
0"
1+
1#
1&
#80
0!
1"
0+
0#
0&
0%
0(
1$
1'
#100
1!
0"
1+
1#
1&
#120
0+
0)
1*
0#
0&
1%
1(
#140
1"
1#
1&
