week-2/q3/simple_circuit.v
module and2(c, b, w1);
    input c, b;
    output w1;
    assign w1 = c & b;
endmodule

module or2(w1, a, d);
    input w1, a;
    output d;
    assign d = w1|a;
endmodule

module circuit3(a2, b2, c2, z);
    input a2, b2, c2;
    output z;
    wire w1, w2, w3;
    and2 M1(c2, b2, w1);
    or2  M2(w1, a2, w2);
    and2 M3(b2, a2, w3);
    or2  M4(w2, w3, z);
endmodule

week-2/q3/simple_circuit_tb.v
module tb_circuit3;
    wire z;
    reg a2, b2, c2;
    circuit3 M1(a2, b2, c2, z);

    initial
    begin
        $dumpfile("circuit3.vcd");
        $dumpvars(1, tb_circuit3);

        a2 = 1'b0; b2 = 1'b0; c2 = 1'b0;
        #20;
        a2 = 1'b0; b2 = 1'b0; c2 = 1'b1;
        #20;
        a2 = 1'b0; b2 = 1'b1; c2 = 1'b0;
        #20;
        a2 = 1'b0; b2 = 1'b1; c2 = 1'b1;
        #20;
        a2 = 1'b1; b2 = 1'b0; c2 = 1'b0;
        #20;
        a2 = 1'b1; b2 = 1'b0; c2 = 1'b1;
        #20;
        a2 = 1'b1; b2 = 1'b1; c2 = 1'b0;
        #20;
        a2 = 1'b1; b2 = 1'b1; c2 = 1'b1;
        #20;

        $finish;
    end
endmodule

week-2/q3/circuit3.vcd
$date
	Thu Aug 13 14:59:08 2026
$end
$version
	Icarus Verilog
$end
$timescale
	1s
$end
$scope module tb_circuit3 $end
$var wire 1 ! z $end
$var reg 1 " a2 $end
$var reg 1 # b2 $end
$var reg 1 $ c2 $end
$upscope $end
$enddefinitions $end
#0
$dumpvars
0$
0#
0"
0!
$end
#20
1$
#40
0$
1#
#60
1!
1$
#80
0$
0#
1"
#100
1$
#120
0$
1#
#140
1$
