week-2/q1/simple_circuit.v
module and2(a, b, w1);
    input a, b;
    output w1;
    assign w1 = a&b;
endmodule


module or2(w1, e, d);
    input w1, e;
    output d;
    assign d = w1|e;
endmodule


module not2(c, e);
    input c;
    output e;
    assign e=!c;
endmodule


module simple_circuit(a, b, c, d, e);
    input a, b, c;
    output d, e;
    wire w1;

    and2 g1(a, b, w1);
    not2 g2(c, e);
    or2 g3(w1, e, d);

endmodule

week-2/q1/simple_circuit_tb.v
module tb_simple_circuit;
wire D, E;
reg A, B, C;

simple_circuit M1 (A, B, C, D, E);
initial
begin
    $dumpfile("simple.vcd");
    $dumpvars(1, tb_simple_circuit);

    A = 1'b0; B = 1'b0; C = 1'b0;
    #20;
    A = 1'b0; B = 1'b0; C = 1'b1;
    #20;
    A = 1'b0; B = 1'b1; C = 1'b0;
    #20;
    A = 1'b0; B = 1'b1; C = 1'b1;
    #20;
    A = 1'b1; B = 1'b0; C = 1'b0;
    #20;
    A = 1'b1; B = 1'b0; C = 1'b1;
    #20;
    A = 1'b1; B = 1'b1; C = 1'b0;
    #20;
    A = 1'b1; B = 1'b1; C = 1'b1;
    #20;
end

initial
#200 $finish;
endmodule

week-2/q1/simple.vcd
$date
	Thu Aug 13 15:00:19 2026
$end
$version
	Icarus Verilog
$end
$timescale
	1s
$end
$scope module tb_simple_circuit $end
$var wire 1 ! D $end
$var wire 1 " E $end
$var reg 1 # A $end
$var reg 1 $ B $end
$var reg 1 % C $end
$upscope $end
$enddefinitions $end
#0
$dumpvars
0%
0$
0#
1"
1!
$end
#20
0!
1%
0"
#40
1!
0%
1"
1$
#60
0!
1%
0"
#80
1!
0%
1"
0$
1#
#100
0!
1%
0"
#120
1!
0%
1"
1$
#140
1%
0"
