week-3/Full-Addder-2/fulladder2.v
module fulladder2(i0, i1, cin, sum, cout);

input i0, i1, cin;
output sum, cout;
assign sum = i0 ^ i1 ^ cin;
assign cout = (i0 & i1) | (i1 & cin) | (i0 & cin);

endmodule

week-3/Full-Addder-2/fulladder2_tb.v
`define TESTVECS 8

module tb_fulladder2;

reg i0, i1, cin;
wire sum, cout;

reg [2:0] test_vecs [0:7];

integer i;

fulladder2 FA1(i0, i1, cin, sum, cout);

initial
begin
    i0 = 0;
    i1 = 0;
    cin = 0;

    $dumpfile("fulladder2.vcd");
    $dumpvars(0, tb_fulladder2);

    for(i = 0; i < `TESTVECS; i = i + 1)
    begin
        #20 {i0, i1, cin} = test_vecs[i];
    end
    #20 $finish;
end

initial
begin
    test_vecs[0] = 3'b000;
    test_vecs[1] = 3'b001;
    test_vecs[2] = 3'b010;
    test_vecs[3] = 3'b011;
    test_vecs[4] = 3'b100;
    test_vecs[5] = 3'b101;
    test_vecs[6] = 3'b110;
    test_vecs[7] = 3'b111;
end

initial
begin
    $monitor($time,
             " i0=%b, i1=%b, cin=%b, sum=%b, cout=%b",
             i0, i1, cin, sum, cout);
end

endmodule

week-3/Full-Addder-2/fulladder2.vcd
$date
	Thu Aug 20 14:55:42 2026
$end
$version
	Icarus Verilog
$end
$timescale
	1s
$end
$scope module tb_fulladder2 $end
$var wire 1 ! cout $end
$var wire 1 " sum $end
$var reg 1 # cin $end
$var integer 32 $ i [31:0] $end
$var reg 1 % i0 $end
$var reg 1 & i1 $end
$scope module FA1 $end
$var wire 1 ' cin $end
$var wire 1 ! cout $end
$var wire 1 ( i0 $end
$var wire 1 ) i1 $end
$var wire 1 " sum $end
$upscope $end
$upscope $end
$enddefinitions $end
#0
$dumpvars
0)
0(
0'
0&
0%
b0 $
0#
0"
0!
$end
#20
b1 $
#40
1"
b10 $
1#
1'
#60
1"
b11 $
1&
1)
0#
0'
#80
1!
0"
b100 $
1#
1'
#100
0!
1"
b101 $
1%
1(
0&
0)
0#
0'
#120
1!
0"
b110 $
1#
1'
#140
1!
0"
b111 $
1&
1)
0#
0'
#160
1"
b1000 $
1#
1'
