week-2/q2/simple_circuit.v
module and2(c, b, w1);
    input c, b;
    output w1;
    assign w1 = c & b;
endmodule


module or2(w1, a, d);
    input w1, a;
    output d;
    assign d = w1 | a;
endmodule

module simple_circuit(a, b, c, d);
    input a, b, c;
    output d;
    wire w1;
    and2 M1(c, b, w1);
    or2  M2(w1, a, d);

endmodule

week-2/q2/simple_circuit_tb.v
module tb_simple_circuit;
    wire d;
    reg a, b, c;

    simple_circuit M1(a, b, c, d);
    initial
    begin
        $dumpfile("simple.vcd");
        $dumpvars(1, tb_simple_circuit);

        a = 1'b0; b = 1'b0; c = 1'b0;
        #20;
        a = 1'b0; b = 1'b0; c = 1'b1;
        #20;
        a = 1'b0; b = 1'b1; c = 1'b0;
        #20;
        a = 1'b0; b = 1'b1; c = 1'b1;
        #20;
        a = 1'b1; b = 1'b0; c = 1'b0;
        #20;
        a = 1'b1; b = 1'b0; c = 1'b1;
        #20;
        a = 1'b1; b = 1'b1; c = 1'b0;
        #20;
        a = 1'b1; b = 1'b1; c = 1'b1;
        #20;
    end

    initial
    #200 $finish;
endmodule

week-2/q2/simple.vcd
$date
	Thu Aug 13 14:44:14 2026
$end
$version
	Icarus Verilog
$end
$timescale
	1s
$end
$scope module tb_simple_circuit $end
$var wire 1 ! d $end
$var reg 1 " a $end
$var reg 1 # b $end
$var reg 1 $ c $end
$upscope $end
$enddefinitions $end
#0
$dumpvars
0$
0#
0"
0!
$end
#20
1$
#40
0$
1#
#60
1!
1$
#80
0$
0#
1"
#100
1$
#120
0$
1#
#140
1$
